unify_live_backend_api_client/__init__.py
unify_live_backend_api_client/api/__init__.py
unify_live_backend_api_client/api/authentication/__init__.py
unify_live_backend_api_client/api/authentication/create_api_credentials.py
unify_live_backend_api_client/api/authentication/exchange_api_credentials_for_token.py
unify_live_backend_api_client/api/authentication/exchange_code_for_token.py
unify_live_backend_api_client/api/chat_clients/__init__.py
unify_live_backend_api_client/api/chat_clients/block_existing_client.py
unify_live_backend_api_client/api/chat_clients/create_new_client.py
unify_live_backend_api_client/api/chat_clients/get_client_activities.py
unify_live_backend_api_client/api/chat_clients/get_integration_blocked_clients.py
unify_live_backend_api_client/api/chat_clients/get_integration_clients.py
unify_live_backend_api_client/api/chat_clients/get_online_clients.py
unify_live_backend_api_client/api/chat_clients/unblock_existing_client.py
unify_live_backend_api_client/api/chat_clients/update_client_presence.py
unify_live_backend_api_client/api/chat_core/__init__.py
unify_live_backend_api_client/api/chat_core/archive_existing_chat.py
unify_live_backend_api_client/api/chat_core/create_new_chat.py
unify_live_backend_api_client/api/chat_core/get_chat_details.py
unify_live_backend_api_client/api/chat_core/get_chat_timestamps.py
unify_live_backend_api_client/api/chat_core/get_chats_by_status.py
unify_live_backend_api_client/api/chat_core/get_integration_chats.py
unify_live_backend_api_client/api/chat_core/update_chat_details.py
unify_live_backend_api_client/api/chat_core/update_chat_status.py
unify_live_backend_api_client/api/chat_messages/__init__.py
unify_live_backend_api_client/api/chat_messages/add_message_attachment.py
unify_live_backend_api_client/api/chat_messages/create_new_message.py
unify_live_backend_api_client/api/chat_messages/delete_message_attachment.py
unify_live_backend_api_client/api/chat_messages/get_all_chat_attachments.py
unify_live_backend_api_client-0.0.1.dist-info/METADATA
unify_live_backend_api_client-0.0.1.dist-info/WHEEL
unify_live_backend_api_client-0.0.1.dist-info/RECORD
